dora/__init__.py
dora/__init__.pyi
dora/builder.py
dora/cuda.py
dora/dora.abi3.so
dora/py.typed
dora_rs_robodriver-0.3.14.dist-info/METADATA
dora_rs_robodriver-0.3.14.dist-info/WHEEL
dora_rs_robodriver-0.3.14.dist-info/RECORD
