Metadata-Version: 2.4
Name: dora-rs-robodriver
Version: 0.3.14
Requires-Dist: pyarrow
Requires-Dist: pyyaml>=6.0
License: MIT
Requires-Python: >=3.7
